http_status_example/__init__.py
http_status_example/main.py
http_status_example/run.py
http_status_example-1.0.7.dist-info/LICENSE
http_status_example-1.0.7.dist-info/METADATA
http_status_example-1.0.7.dist-info/WHEEL
http_status_example-1.0.7.dist-info/entry_points.txt
http_status_example-1.0.7.dist-info/top_level.txt
http_status_example-1.0.7.dist-info/RECORD
