Metadata-Version: 2.1
Name: http-status-example
Version: 1.0.7
Summary: prints the HTTP status code of the url provided by the user
Home-page: UNKNOWN
Author: Russ Nastala
License: MIT
Platform: UNKNOWN
Classifier: License :: OSI Approved :: MIT License
Requires-Python: ~=3.8
License-File: LICENSE
Requires-Dist: requests ~=2.32
